LICENSE
MANIFEST.in
README.md
README.rst
RELEASE-VERSION
setup.py
version.py
dossier/__init__.py
dossier.label.egg-info/PKG-INFO
dossier.label.egg-info/SOURCES.txt
dossier.label.egg-info/dependency_links.txt
dossier.label.egg-info/entry_points.txt
dossier.label.egg-info/namespace_packages.txt
dossier.label.egg-info/not-zip-safe
dossier.label.egg-info/requires.txt
dossier.label.egg-info/top_level.txt
dossier/label/__init__.py
dossier/label/combined_store.py
dossier/label/label.py
dossier/label/relation_label.py
dossier/label/run.py
dossier/label/tests/__init__.py
dossier/label/tests/bench_label_objects.py
dossier/label/tests/test_combined_store.py
dossier/label/tests/test_label.py
dossier/label/tests/test_label_store.py
dossier/label/tests/test_relation_label.py
dossier/label/tests/test_relation_label_store.py
dossier/label/tests/test_run.py