Metadata-Version: 1.1
Name: dossier.label
Version: 0.4.8
Summary: Label (ground truth) storage for DossierStack
Home-page: https://github.com/dossier/dossier.label
Author: Diffeo, Inc.
Author-email: support@diffeo.com
License: MIT
Platform: UNKNOWN
Classifier: Development Status :: 3 - Alpha
Classifier: Topic :: Utilities
Classifier: License :: OSI Approved :: MIT License
